setup.py
common/__init__.py
common/decorators.py
common/descriptors.py
common/errors.py
common/metaclasses.py
common/utilities.py
common/vars.py
logs/__init__.py
logs/configs_logs/__init__.py
logs/configs_logs/config_client_log.py
logs/configs_logs/config_server_log.py
project_unittests/__init__.py
project_unittests/test_client.py
project_unittests/test_server.py
project_unittests/test_utils.py
server/__init__.py
server/add_user.py
server/cl_history_window.py
server/main.py
server/main_window.py
server/remove_user.py
server/server_db.py
server/window_config.py
server_mess_app.egg-info/PKG-INFO
server_mess_app.egg-info/SOURCES.txt
server_mess_app.egg-info/dependency_links.txt
server_mess_app.egg-info/requires.txt
server_mess_app.egg-info/top_level.txt